Workbook

Sheet Dashboard
B2: FnB Sales Performance Dashboard
B4: ="Trading period: "&'Summary KPIs'!B2&" to "&'Summary KPIs'!B3&" | "&'Summary KPIs'!B4&" trading days" -> Trading period: 2013-12-30 to 2016-11-16 | 1053 trading days
B6: Total Sales (R) | G6: Total Cost of Sales (R) | L6: Total Gross Profit (R) | Q6: Total Quantity Sold | V6: Avg Daily Gross Profit % | AA6: Avg Unit Sales Price (R)
B7: ='Summary KPIs'!B5 -> 1.8690983e+08 | G7: ='Summary KPIs'!B6 -> 1.9402611e+08 | L7: ='Summary KPIs'!B5-'Summary KPIs'!B6 -> -7116281.2 | Q7: ='Summary KPIs'!B7 -> 5279872 | V7: ='Summary KPIs'!B9 -> -0.038073339 | AA7: ='Summary KPIs'!B8 -> 35.400447
B11: Key Trends & Analysis
B79: Underlying pivot tables and detailed data are on the tabs to the right (Sales Master, Summary KPIs, Promo & Elasticity, Monthly Pivot, Day of Week Pivot).

Sheet Sales Master
A1: Date | B1: Sales (R) | C1: Cost of Sales (R) | D1: Quantity Sold | E1: Price per Unit (R) | F1: Cost per Unit (R) | G1: Gross Profit (R) | H1: Gross Profit % | I1: Gross Profit per Unit (R) | J1: Gross Profit % per Unit | K1: Day of Week | L1: Period Label
A2: 41638 | B2: 223937.97 | C2: 230079.62 | D2: 6827 | E2: =B2/D2 -> 32.801812 | F2: =C2/D2 -> 33.701424 | G2: =B2-C2 -> -6141.6531 | H2: =G2/B2 -> -0.027425689 | I2: =G2/D2 -> -0.8996123 | J2: =I2/E2 -> -0.027425689 | K2: =TEXT(A2,"dddd") -> Monday | L2: =IF(AND(A2>=DATE(2014,9,24),A2<=DATE(2014,10,6)),"Promo 1",IF(AND(A2>=DATE(2014,9,10),A2<=DATE(2014,9,23)),"Baseline 1",IF(AND(A2>=DATE(2015,9,23),A2<=DATE(2015,10,6)),"Promo 2",IF(AND(A2>=DATE(2015,9,9),A2<=DATE(2015,9,22)),"Baseline 2",IF(AND(A2>=DATE(2016,6,23),A2<=DATE(2016,7,6)),"Promo 3",IF(AND(A2>=DATE(2016,6,9),A2<=DATE(2016,6,22)),"Baseline 3","Other")))))) -> Other
A3: 41639 | B3: 300345.48 | C3: 306986.12 | D3: 9268 | E3: =B3/D3 -> 32.40672 | F3: =C3/D3 -> 33.123233 | G3: =B3-C3 -> -6640.6359 | H3: =G3/B3 -> -0.022109991 | I3: =G3/D3 -> -0.71651229 | J3: =I3/E3 -> -0.022109991 | K3: =TEXT(A3,"dddd") -> Tuesday | L3: =IF(AND(A3>=DATE(2014,9,24),A3<=DATE(2014,10,6)),"Promo 1",IF(AND(A3>=DATE(2014,9,10),A3<=DATE(2014,9,23)),"Baseline 1",IF(AND(A3>=DATE(2015,9,23),A3<=DATE(2015,10,6)),"Promo 2",IF(AND(A3>=DATE(2015,9,9),A3<=DATE(2015,9,22)),"Baseline 2",IF(AND(A3>=DATE(2016,6,23),A3<=DATE(2016,7,6)),"Promo 3",IF(AND(A3>=DATE(2016,6,9),A3<=DATE(2016,6,22)),"Baseline 3","Other")))))) -> Other
A4: 41640 | B4: 86782.468 | C4: 87986.318 | D4: 2678 | E4: =B4/D4 -> 32.405701 | F4: =C4/D4 -> 32.855235 | G4: =B4-C4 -> -1203.8505 | H4: =G4/B4 -> -0.013872047 | I4: =G4/D4 -> -0.44953342 | J4: =I4/E4 -> -0.013872047 | K4: =TEXT(A4,"dddd") -> Wednesday | L4: =IF(AND(A4>=DATE(2014,9,24),A4<=DATE(2014,10,6)),"Promo 1",IF(AND(A4>=DATE(2014,9,10),A4<=DATE(2014,9,23)),"Baseline 1",IF(AND(A4>=DATE(2015,9,23),A4<=DATE(2015,10,6)),"Promo 2",IF(AND(A4>=DATE(2015,9,9),A4<=DATE(2015,9,22)),"Baseline 2",IF(AND(A4>=DATE(2016,6,23),A4<=DATE(2016,7,6)),"Promo 3",IF(AND(A4>=DATE(2016,6,9),A4<=DATE(2016,6,22)),"Baseline 3","Other")))))) -> Other
A5: 41641 | B5: 200173.12 | C5: 202881.18 | D5: 6175 | E5: =B5/D5 -> 32.416699 | F5: =C5/D5 -> 32.855251 | G5: =B5-C5 -> -2708.061 | H5: =G5/B5 -> -0.013528595 | I5: =G5/D5 -> -0.43855238 | J5: =I5/E5 -> -0.013528595 | K5: =TEXT(A5,"dddd") -> Thursday | L5: =IF(AND(A5>=DATE(2014,9,24),A5<=DATE(2014,10,6)),"Promo 1",IF(AND(A5>=DATE(2014,9,10),A5<=DATE(2014,9,23)),"Baseline 1",IF(AND(A5>=DATE(2015,9,23),A5<=DATE(2015,10,6)),"Promo 2",IF(AND(A5>=DATE(2015,9,9),A5<=DATE(2015,9,22)),"Baseline 2",IF(AND(A5>=DATE(2016,6,23),A5<=DATE(2016,7,6)),"Promo 3",IF(AND(A5>=DATE(2016,6,9),A5<=DATE(2016,6,22)),"Baseline 3","Other")))))) -> Other
A6: 41642 | B6: 326906.07 | C6: 333806.29 | D6: 10084 | E6: =B6/D6 -> 32.418294 | F6: =C6/D6 -> 33.102568 | G6: =B6-C6 -> -6900.2177 | H6: =G6/B6 -> -0.021107646 | I6: =G6/D6 -> -0.68427387 | J6: =I6/E6 -> -0.021107646 | K6: =TEXT(A6,"dddd") -> Friday | L6: =IF(AND(A6>=DATE(2014,9,24),A6<=DATE(2014,10,6)),"Promo 1",IF(AND(A6>=DATE(2014,9,10),A6<=DATE(2014,9,23)),"Baseline 1",IF(AND(A6>=DATE(2015,9,23),A6<=DATE(2015,10,6)),"Promo 2",IF(AND(A6>=DATE(2015,9,9),A6<=DATE(2015,9,22)),"Baseline 2",IF(AND(A6>=DATE(2016,6,23),A6<=DATE(2016,7,6)),"Promo 3",IF(AND(A6>=DATE(2016,6,9),A6<=DATE(2016,6,22)),"Baseline 3","Other")))))) -> Other
A7: 41643 | B7: 307043.94 | C7: 313652.35 | D7: 9470 | E7: =B7/D7 -> 32.422802 | F7: =C7/D7 -> 33.120628 | G7: =B7-C7 -> -6608.4129 | H7: =G7/B7 -> -0.021522695 | I7: =G7/D7 -> -0.69782607 | J7: =I7/E7 -> -0.021522695 | K7: =TEXT(A7,"dddd") -> Saturday | L7: =IF(AND(A7>=DATE(2014,9,24),A7<=DATE(2014,10,6)),"Promo 1",IF(AND(A7>=DATE(2014,9,10),A7<=DATE(2014,9,23)),"Baseline 1",IF(AND(A7>=DATE(2015,9,23),A7<=DATE(2015,10,6)),"Promo 2",IF(AND(A7>=DATE(2015,9,9),A7<=DATE(2015,9,22)),"Baseline 2",IF(AND(A7>=DATE(2016,6,23),A7<=DATE(2016,7,6)),"Promo 3",IF(AND(A7>=DATE(2016,6,9),A7<=DATE(2016,6,22)),"Baseline 3","Other")))))) -> Other
A8: 41644 | B8: 179188.88 | C8: 183083.28 | D8: 5524 | E8: =B8/D8 -> 32.438248 | F8: =C8/D8 -> 33.143245 | G8: =B8-C8 -> -3894.4005 | H8: =G8/B8 -> -0.021733494 | I8: =G8/D8 -> -0.70499647 | J8: =I8/E8 -> -0.021733494 | K8: =TEXT(A8,"dddd") -> Sunday | L8: =IF(AND(A8>=DATE(2014,9,24),A8<=DATE(2014,10,6)),"Promo 1",IF(AND(A8>=DATE(2014,9,10),A8<=DATE(2014,9,23)),"Baseline 1",IF(AND(A8>=DATE(2015,9,23),A8<=DATE(2015,10,6)),"Promo 2",IF(AND(A8>=DATE(2015,9,9),A8<=DATE(2015,9,22)),"Baseline 2",IF(AND(A8>=DATE(2016,6,23),A8<=DATE(2016,7,6)),"Promo 3",IF(AND(A8>=DATE(2016,6,9),A8<=DATE(2016,6,22)),"Baseline 3","Other")))))) -> Other
A9: 41645 | B9: 306351.95 | C9: 313446.07 | D9: 9448 | E9: =B9/D9 -> 32.425058 | F9: =C9/D9 -> 33.175917 | G9: =B9-C9 -> -7094.1173 | H9: =G9/B9 -> -0.023156756 | I9: =G9/D9 -> -0.75085915 | J9: =I9/E9 -> -0.023156756 | K9: =TEXT(A9,"dddd") -> Monday | L9: =IF(AND(A9>=DATE(2014,9,24),A9<=DATE(2014,10,6)),"Promo 1",IF(AND(A9>=DATE(2014,9,10),A9<=DATE(2014,9,23)),"Baseline 1",IF(AND(A9>=DATE(2015,9,23),A9<=DATE(2015,10,6)),"Promo 2",IF(AND(A9>=DATE(2015,9,9),A9<=DATE(2015,9,22)),"Baseline 2",IF(AND(A9>=DATE(2016,6,23),A9<=DATE(2016,7,6)),"Promo 3",IF(AND(A9>=DATE(2016,6,9),A9<=DATE(2016,6,22)),"Baseline 3","Other")))))) -> Other
A10: 41646 | B10: 224020.41 | C10: 229533.97 | D10: 6911 | E10: =B10/D10 -> 32.41505 | F10: =C10/D10 -> 33.212845 | G10: =B10-C10 -> -5513.5638 | H10: =G10/B10 -> -0.024611881 | I10: =G10/D10 -> -0.79779536 | J10: =I10/E10 -> -0.024611881 | K10: =TEXT(A10,"dddd") -> Tuesday | L10: =IF(AND(A10>=DATE(2014,9,24),A10<=DATE(2014,10,6)),"Promo 1",IF(AND(A10>=DATE(2014,9,10),A10<=DATE(2014,9,23)),"Baseline 1",IF(AND(A10>=DATE(2015,9,23),A10<=DATE(2015,10,6)),"Promo 2",IF(AND(A10>=DATE(2015,9,9),A10<=DATE(2015,9,22)),"Baseline 2",IF(AND(A10>=DATE(2016,6,23),A10<=DATE(2016,7,6)),"Promo 3",IF(AND(A10>=DATE(2016,6,9),A10<=DATE(2016,6,22)),"Baseline 3","Other")))))) -> Other
A11: 41647 | B11: 101836.4 | C11: 99381.968 | D11: 2990 | E11: =B11/D11 -> 34.058997 | F11: =C11/D11 -> 33.238116 | G11: =B11-C11 -> 2454.4347 | H11: =G11/B11 -> 0.024101742 | I11: =G11/D11 -> 0.82088118 | J11: =I11/E11 -> 0.024101742 | K11: =TEXT(A11,"dddd") -> Wednesday | L11: =IF(AND(A11>=DATE(2014,9,24),A11<=DATE(2014,10,6)),"Promo 1",IF(AND(A11>=DATE(2014,9,10),A11<=DATE(2014,9,23)),"Baseline 1",IF(AND(A11>=DATE(2015,9,23),A11<=DATE(2015,10,6)),"Promo 2",IF(AND(A11>=DATE(2015,9,9),A11<=DATE(2015,9,22)),"Baseline 2",IF(AND(A11>=DATE(2016,6,23),A11<=DATE(2016,7,6)),"Promo 3",IF(AND(A11>=DATE(2016,6,9),A11<=DATE(2016,6,22)),"Baseline 3","Other")))))) -> Other
A12: 41648 | B12: 107804.3 | C12: 104816.46 | D12: 3159 | E12: =B12/D12 -> 34.126086 | F12: =C12/D12 -> 33.180265 | G12: =B12-C12 -> 2987.8464 | H12: =G12/B12 -> 0.027715465 | I12: =G12/D12 -> 0.94582033 | J12: =I12/E12 -> 0.027715465 | K12: =TEXT(A12,"dddd") -> Thursday | L12: =IF(AND(A12>=DATE(2014,9,24),A12<=DATE(2014,10,6)),"Promo 1",IF(AND(A12>=DATE(2014,9,10),A12<=DATE(2014,9,23)),"Baseline 1",IF(AND(A12>=DATE(2015,9,23),A12<=DATE(2015,10,6)),"Promo 2",IF(AND(A12>=DATE(2015,9,9),A12<=DATE(2015,9,22)),"Baseline 2",IF(AND(A12>=DATE(2016,6,23),A12<=DATE(2016,7,6)),"Promo 3",IF(AND(A12>=DATE(2016,6,9),A12<=DATE(2016,6,22)),"Baseline 3","Other")))))) -> Other
A13: 41649 | B13: 144829.96 | C13: 141334 | D13: 4246 | E13: =B13/D13 -> 34.10974 | F13: =C13/D13 -> 33.286386 | G13: =B13-C13 -> 3495.9604 | H13: =G13/B13 -> 0.024138379 | I13: =G13/D13 -> 0.82335385 | J13: =I13/E13 -> 0.024138379 | K13: =TEXT(A13,"dddd") -> Friday | L13: =IF(AND(A13>=DATE(2014,9,24),A13<=DATE(2014,10,6)),"Promo 1",IF(AND(A13>=DATE(2014,9,10),A13<=DATE(2014,9,23)),"Baseline 1",IF(AND(A13>=DATE(2015,9,23),A13<=DATE(2015,10,6)),"Promo 2",IF(AND(A13>=DATE(2015,9,9),A13<=DATE(2015,9,22)),"Baseline 2",IF(AND(A13>=DATE(2016,6,23),A13<=DATE(2016,7,6)),"Promo 3",IF(AND(A13>=DATE(2016,6,9),A13<=DATE(2016,6,22)),"Baseline 3","Other")))))) -> Other
... A1054: 42690 | B1054: 77229.972 | C1054: 71428.87 | D1054: 1763 | E1054: =B1054/D1054 -> 43.805997 | F1054: =C1054/D1054 -> 40.515525 | G1054: =B1054-C1054 -> 5801.1019 | H1054: =G1054/B1054 -> 0.075114645 | I1054: =G1054/D1054 -> 3.2904719 | J1054: =I1054/E1054 -> 0.075114645 | K1054: =TEXT(A1054,"dddd") -> Wednesday | L1054: =IF(AND(A1054>=DATE(2014,9,24),A1054<=DATE(2014,10,6)),"Promo 1",IF(AND(A1054>=DATE(2014,9,10),A1054<=DATE(2014,9,23)),"Baseline 1",IF(AND(A1054>=DATE(2015,9,23),A1054<=DATE(2015,10,6)),"Promo 2",IF(AND(A1054>=DATE(2015,9,9),A1054<=DATE(2015,9,22)),"Baseline 2",IF(AND(A1054>=DATE(2016,6,23),A1054<=DATE(2016,7,6)),"Promo 3",IF(AND(A1054>=DATE(2016,6,9),A1054<=DATE(2016,6,22)),"Baseline 3","Other")))))) -> Other

Sheet Summary KPIs
A1: Metric | B1: Value
A2: Date Range Start | B2: =TEXT(MIN('Sales Master'!A2:A1054),"yyyy-mm-dd") -> 2013-12-30
A3: Date Range End | B3: =TEXT(MAX('Sales Master'!A2:A1054),"yyyy-mm-dd") -> 2016-11-16
A4: Number of Trading Days | B4: =COUNT('Sales Master'!A2:A1054) -> 1053
A5: Total Sales (R) | B5: =SUM('Sales Master'!B2:B1054) -> 1.8690983e+08
A6: Total Cost of Sales (R) | B6: =SUM('Sales Master'!C2:C1054) -> 1.9402611e+08
A7: Total Quantity Sold | B7: =SUM('Sales Master'!D2:D1054) -> 5279872
A8: Average Unit Sales Price (R) | B8: =SUM('Sales Master'!B2:B1054)/SUM('Sales Master'!D2:D1054) -> 35.400447
A9: Average Daily Gross Profit % | B9: =SUM('Sales Master'!G2:G1054)/SUM('Sales Master'!B2:B1054) -> -0.038073339
A10: Min Daily Price per Unit (R) | B10: =MIN('Sales Master'!E2:E1054) -> 30.70237
A11: Max Daily Price per Unit (R) | B11: =MAX('Sales Master'!E2:E1054) -> 43.805997
A12: Std Dev of Daily Price per Unit | B12: =STDEV('Sales Master'!E2:E1054) -> 3.445058

Sheet Promo & Elasticity
A1: Period # | B1: Promo Start | C1: Promo End | D1: Baseline Start | E1: Baseline End | F1: Baseline Avg Price (R) | G1: Baseline Avg Qty | H1: Promo Avg Price (R) | I1: Promo Avg Qty | J1: % Change Price | K1: % Change Qty | L1: Price Elasticity of Demand (PED) | M1: Baseline Total GP (R)* | N1: Promo Total GP (R)*
A2: 1 | B2: 2014-09-24 | C2: 2014-10-06 | D2: 2014-09-10 | E2: 2014-09-23 | F2: =AVERAGEIFS('Sales Master'!$E$2:$E$1054,'Sales Master'!$A$2:$A$1054,">="&D2,'Sales Master'!$A$2:$A$1054,"<="&E2) -> 35.036017 | G2: =AVERAGEIFS('Sales Master'!$D$2:$D$1054,'Sales Master'!$A$2:$A$1054,">="&D2,'Sales Master'!$A$2:$A$1054,"<="&E2) -> 2997.5714 | H2: =AVERAGEIFS('Sales Master'!$E$2:$E$1054,'Sales Master'!$A$2:$A$1054,">="&B2,'Sales Master'!$A$2:$A$1054,"<="&C2) -> 32.451836 | I2: =AVERAGEIFS('Sales Master'!$D$2:$D$1054,'Sales Master'!$A$2:$A$1054,">="&B2,'Sales Master'!$A$2:$A$1054,"<="&C2) -> 13210.077 | J2: =(H2-F2)/F2 -> -0.073757828 | K2: =(I2-G2)/G2 -> 3.4069265 | L2: =K2/J2 -> -46.190711 | M2: =SUMIFS('Sales Master'!$G$2:$G$1054,'Sales Master'!$A$2:$A$1054,">="&D2,'Sales Master'!$A$2:$A$1054,"<="&E2) -> 23880.563 | N2: =SUMIFS('Sales Master'!$G$2:$G$1054,'Sales Master'!$A$2:$A$1054,">="&B2,'Sales Master'!$A$2:$A$1054,"<="&C2) -> -408820.22
A3: 2 | B3: 2015-09-23 | C3: 2015-10-06 | D3: 2015-09-09 | E3: 2015-09-22 | F3: =AVERAGEIFS('Sales Master'!$E$2:$E$1054,'Sales Master'!$A$2:$A$1054,">="&D3,'Sales Master'!$A$2:$A$1054,"<="&E3) -> 39.137513 | G3: =AVERAGEIFS('Sales Master'!$D$2:$D$1054,'Sales Master'!$A$2:$A$1054,">="&D3,'Sales Master'!$A$2:$A$1054,"<="&E3) -> 1339.4286 | H3: =AVERAGEIFS('Sales Master'!$E$2:$E$1054,'Sales Master'!$A$2:$A$1054,">="&B3,'Sales Master'!$A$2:$A$1054,"<="&C3) -> 33.396349 | I3: =AVERAGEIFS('Sales Master'!$D$2:$D$1054,'Sales Master'!$A$2:$A$1054,">="&B3,'Sales Master'!$A$2:$A$1054,"<="&C3) -> 8089.3571 | J3: =(H3-F3)/F3 -> -0.1466921 | K3: =(I3-G3)/G3 -> 5.0394091 | L3: =K3/J3 -> -34.353651 | M3: =SUMIFS('Sales Master'!$G$2:$G$1054,'Sales Master'!$A$2:$A$1054,">="&D3,'Sales Master'!$A$2:$A$1054,"<="&E3) -> 39435.964 | N3: =SUMIFS('Sales Master'!$G$2:$G$1054,'Sales Master'!$A$2:$A$1054,">="&B3,'Sales Master'!$A$2:$A$1054,"<="&C3) -> -515054.19
A4: 3 | B4: 2016-06-23 | C4: 2016-07-06 | D4: 2016-06-09 | E4: 2016-06-22 | F4: =AVERAGEIFS('Sales Master'!$E$2:$E$1054,'Sales Master'!$A$2:$A$1054,">="&D4,'Sales Master'!$A$2:$A$1054,"<="&E4) -> 35.416435 | G4: =AVERAGEIFS('Sales Master'!$D$2:$D$1054,'Sales Master'!$A$2:$A$1054,">="&D4,'Sales Master'!$A$2:$A$1054,"<="&E4) -> 5250.0714 | H4: =AVERAGEIFS('Sales Master'!$E$2:$E$1054,'Sales Master'!$A$2:$A$1054,">="&B4,'Sales Master'!$A$2:$A$1054,"<="&C4) -> 33.392058 | I4: =AVERAGEIFS('Sales Master'!$D$2:$D$1054,'Sales Master'!$A$2:$A$1054,">="&B4,'Sales Master'!$A$2:$A$1054,"<="&C4) -> 8653.6429 | J4: =(H4-F4)/F4 -> -0.057159245 | K4: =(I4-G4)/G4 -> 0.6482905 | L4: =K4/J4 -> -11.341831 | M4: =SUMIFS('Sales Master'!$G$2:$G$1054,'Sales Master'!$A$2:$A$1054,">="&D4,'Sales Master'!$A$2:$A$1054,"<="&E4) -> -106753.18 | N4: =SUMIFS('Sales Master'!$G$2:$G$1054,'Sales Master'!$A$2:$A$1054,">="&B4,'Sales Master'!$A$2:$A$1054,"<="&C4) -> -328474.41
A6: Interpretation
A7: All three periods show highly elastic demand (|PED| >> 1): a small % reduction in price during promotional windows is associated with a very large % increase in units sold, and total Rand revenue and gross profit Rand value rise even though the unit margin % is compressed. This product therefore performs materially better in volume and revenue terms when on promotion; the trade-off is a lower gross profit % per unit, so the promotion is only worthwhile while the extra volume more than compensates for the thinner margin (see Total Gross Profit comparison).
A8: *Baseline/Promo Total GP compares total gross profit earned over the (differently-sized) baseline vs promo windows shown in columns D:E and B:C — a directional check, not a like-for-like daily rate.

Sheet Monthly Pivot
A1: Month | B1: Total Sales (R) | C1: Total Cost of Sales (R) | D1: Total Quantity Sold | E1: Total Gross Profit (R) | F1: Gross Profit % | G1: Avg Price per Unit (R)
A2: 41609 | B2: =SUMIFS('Sales Master'!$B$2:$B$1054,'Sales Master'!$A$2:$A$1054,">="&A2,'Sales Master'!$A$2:$A$1054,"<="&DATE(YEAR(A2),MONTH(A2)+1,1)-1) -> 524283.45 | C2: =SUMIFS('Sales Master'!$C$2:$C$1054,'Sales Master'!$A$2:$A$1054,">="&A2,'Sales Master'!$A$2:$A$1054,"<="&DATE(YEAR(A2),MONTH(A2)+1,1)-1) -> 537065.74 | D2: =SUMIFS('Sales Master'!$D$2:$D$1054,'Sales Master'!$A$2:$A$1054,">="&A2,'Sales Master'!$A$2:$A$1054,"<="&DATE(YEAR(A2),MONTH(A2)+1,1)-1) -> 16095 | E2: =B2-C2 -> -12782.289 | F2: =E2/B2 -> -0.024380493 | G2: =B2/D2 -> 32.574306
A3: 41640 | B3: =SUMIFS('Sales Master'!$B$2:$B$1054,'Sales Master'!$A$2:$A$1054,">="&A3,'Sales Master'!$A$2:$A$1054,"<="&DATE(YEAR(A3),MONTH(A3)+1,1)-1) -> 4008180.5 | C3: =SUMIFS('Sales Master'!$C$2:$C$1054,'Sales Master'!$A$2:$A$1054,">="&A3,'Sales Master'!$A$2:$A$1054,"<="&DATE(YEAR(A3),MONTH(A3)+1,1)-1) -> 3995719.8 | D3: =SUMIFS('Sales Master'!$D$2:$D$1054,'Sales Master'!$A$2:$A$1054,">="&A3,'Sales Master'!$A$2:$A$1054,"<="&DATE(YEAR(A3),MONTH(A3)+1,1)-1) -> 119965 | E3: =B3-C3 -> 12460.645 | F3: =E3/B3 -> 0.0031088035 | G3: =B3/D3 -> 33.411249
A4: 41671 | B4: =SUMIFS('Sales Master'!$B$2:$B$1054,'Sales Master'!$A$2:$A$1054,">="&A4,'Sales Master'!$A$2:$A$1054,"<="&DATE(YEAR(A4),MONTH(A4)+1,1)-1) -> 5780487.2 | C4: =SUMIFS('Sales Master'!$C$2:$C$1054,'Sales Master'!$A$2:$A$1054,">="&A4,'Sales Master'!$A$2:$A$1054,"<="&DATE(YEAR(A4),MONTH(A4)+1,1)-1) -> 5913478.6 | D4: =SUMIFS('Sales Master'!$D$2:$D$1054,'Sales Master'!$A$2:$A$1054,">="&A4,'Sales Master'!$A$2:$A$1054,"<="&DATE(YEAR(A4),MONTH(A4)+1,1)-1) -> 178035 | E4: =B4-C4 -> -132991.39 | F4: =E4/B4 -> -0.023006951 | G4: =B4/D4 -> 32.468263
A5: 41699 | B5: =SUMIFS('Sales Master'!$B$2:$B$1054,'Sales Master'!$A$2:$A$1054,">="&A5,'Sales Master'!$A$2:$A$1054,"<="&DATE(YEAR(A5),MONTH(A5)+1,1)-1) -> 8279517.2 | C5: =SUMIFS('Sales Master'!$C$2:$C$1054,'Sales Master'!$A$2:$A$1054,">="&A5,'Sales Master'!$A$2:$A$1054,"<="&DATE(YEAR(A5),MONTH(A5)+1,1)-1) -> 8415654 | D5: =SUMIFS('Sales Master'!$D$2:$D$1054,'Sales Master'!$A$2:$A$1054,">="&A5,'Sales Master'!$A$2:$A$1054,"<="&DATE(YEAR(A5),MONTH(A5)+1,1)-1) -> 252836 | E5: =B5-C5 -> -136136.84 | F5: =E5/B5 -> -0.016442607 | G5: =B5/D5 -> 32.746591
A6: 41730 | B6: =SUMIFS('Sales Master'!$B$2:$B$1054,'Sales Master'!$A$2:$A$1054,">="&A6,'Sales Master'!$A$2:$A$1054,"<="&DATE(YEAR(A6),MONTH(A6)+1,1)-1) -> 6435743.3 | C6: =SUMIFS('Sales Master'!$C$2:$C$1054,'Sales Master'!$A$2:$A$1054,">="&A6,'Sales Master'!$A$2:$A$1054,"<="&DATE(YEAR(A6),MONTH(A6)+1,1)-1) -> 6479643.6 | D6: =SUMIFS('Sales Master'!$D$2:$D$1054,'Sales Master'!$A$2:$A$1054,">="&A6,'Sales Master'!$A$2:$A$1054,"<="&DATE(YEAR(A6),MONTH(A6)+1,1)-1) -> 190091 | E6: =B6-C6 -> -43900.351 | F6: =E6/B6 -> -0.0068213335 | G6: =B6/D6 -> 33.856118
A7: 41760 | B7: =SUMIFS('Sales Master'!$B$2:$B$1054,'Sales Master'!$A$2:$A$1054,">="&A7,'Sales Master'!$A$2:$A$1054,"<="&DATE(YEAR(A7),MONTH(A7)+1,1)-1) -> 7694906.2 | C7: =SUMIFS('Sales Master'!$C$2:$C$1054,'Sales Master'!$A$2:$A$1054,">="&A7,'Sales Master'!$A$2:$A$1054,"<="&DATE(YEAR(A7),MONTH(A7)+1,1)-1) -> 8017240.4 | D7: =SUMIFS('Sales Master'!$D$2:$D$1054,'Sales Master'!$A$2:$A$1054,">="&A7,'Sales Master'!$A$2:$A$1054,"<="&DATE(YEAR(A7),MONTH(A7)+1,1)-1) -> 235793 | E7: =B7-C7 -> -322334.26 | F7: =E7/B7 -> -0.041889304 | G7: =B7/D7 -> 32.634159
A8: 41791 | B8: =SUMIFS('Sales Master'!$B$2:$B$1054,'Sales Master'!$A$2:$A$1054,">="&A8,'Sales Master'!$A$2:$A$1054,"<="&DATE(YEAR(A8),MONTH(A8)+1,1)-1) -> 6456943.6 | C8: =SUMIFS('Sales Master'!$C$2:$C$1054,'Sales Master'!$A$2:$A$1054,">="&A8,'Sales Master'!$A$2:$A$1054,"<="&DATE(YEAR(A8),MONTH(A8)+1,1)-1) -> 6645843.7 | D8: =SUMIFS('Sales Master'!$D$2:$D$1054,'Sales Master'!$A$2:$A$1054,">="&A8,'Sales Master'!$A$2:$A$1054,"<="&DATE(YEAR(A8),MONTH(A8)+1,1)-1) -> 198857 | E8: =B8-C8 -> -188900.01 | F8: =E8/B8 -> -0.029255329 | G8: =B8/D8 -> 32.470286
A9: 41821 | B9: =SUMIFS('Sales Master'!$B$2:$B$1054,'Sales Master'!$A$2:$A$1054,">="&A9,'Sales Master'!$A$2:$A$1054,"<="&DATE(YEAR(A9),MONTH(A9)+1,1)-1) -> 4933710.8 | C9: =SUMIFS('Sales Master'!$C$2:$C$1054,'Sales Master'!$A$2:$A$1054,">="&A9,'Sales Master'!$A$2:$A$1054,"<="&DATE(YEAR(A9),MONTH(A9)+1,1)-1) -> 5004894.9 | D9: =SUMIFS('Sales Master'!$D$2:$D$1054,'Sales Master'!$A$2:$A$1054,">="&A9,'Sales Master'!$A$2:$A$1054,"<="&DATE(YEAR(A9),MONTH(A9)+1,1)-1) -> 147449 | E9: =B9-C9 -> -71184.101 | F9: =E9/B9 -> -0.014428106 | G9: =B9/D9 -> 33.460456
A10: 41852 | B10: =SUMIFS('Sales Master'!$B$2:$B$1054,'Sales Master'!$A$2:$A$1054,">="&A10,'Sales Master'!$A$2:$A$1054,"<="&DATE(YEAR(A10),MONTH(A10)+1,1)-1) -> 10010378 | C10: =SUMIFS('Sales Master'!$C$2:$C$1054,'Sales Master'!$A$2:$A$1054,">="&A10,'Sales Master'!$A$2:$A$1054,"<="&DATE(YEAR(A10),MONTH(A10)+1,1)-1) -> 10524432 | D10: =SUMIFS('Sales Master'!$D$2:$D$1054,'Sales Master'!$A$2:$A$1054,">="&A10,'Sales Master'!$A$2:$A$1054,"<="&DATE(YEAR(A10),MONTH(A10)+1,1)-1) -> 310572 | E10: =B10-C10 -> -514054.14 | F10: =E10/B10 -> -0.051352119 | G10: =B10/D10 -> 32.232069
A11: 41883 | B11: =SUMIFS('Sales Master'!$B$2:$B$1054,'Sales Master'!$A$2:$A$1054,">="&A11,'Sales Master'!$A$2:$A$1054,"<="&DATE(YEAR(A11),MONTH(A11)+1,1)-1) -> 7643452.7 | C11: =SUMIFS('Sales Master'!$C$2:$C$1054,'Sales Master'!$A$2:$A$1054,">="&A11,'Sales Master'!$A$2:$A$1054,"<="&DATE(YEAR(A11),MONTH(A11)+1,1)-1) -> 8193560 | D11: =SUMIFS('Sales Master'!$D$2:$D$1054,'Sales Master'!$A$2:$A$1054,">="&A11,'Sales Master'!$A$2:$A$1054,"<="&DATE(YEAR(A11),MONTH(A11)+1,1)-1) -> 237742 | E11: =B11-C11 -> -550107.35 | F11: =E11/B11 -> -0.071971055 | G11: =B11/D11 -> 32.150199
A12: 41913 | B12: =SUMIFS('Sales Master'!$B$2:$B$1054,'Sales Master'!$A$2:$A$1054,">="&A12,'Sales Master'!$A$2:$A$1054,"<="&DATE(YEAR(A12),MONTH(A12)+1,1)-1) -> 5924683.4 | C12: =SUMIFS('Sales Master'!$C$2:$C$1054,'Sales Master'!$A$2:$A$1054,">="&A12,'Sales Master'!$A$2:$A$1054,"<="&DATE(YEAR(A12),MONTH(A12)+1,1)-1) -> 6038461.3 | D12: =SUMIFS('Sales Master'!$D$2:$D$1054,'Sales Master'!$A$2:$A$1054,">="&A12,'Sales Master'!$A$2:$A$1054,"<="&DATE(YEAR(A12),MONTH(A12)+1,1)-1) -> 171709 | E12: =B12-C12 -> -113777.94 | F12: =E12/B12 -> -0.019204053 | G12: =B12/D12 -> 34.50421
A13: 41944 | B13: =SUMIFS('Sales Master'!$B$2:$B$1054,'Sales Master'!$A$2:$A$1054,">="&A13,'Sales Master'!$A$2:$A$1054,"<="&DATE(YEAR(A13),MONTH(A13)+1,1)-1) -> 2631353.3 | C13: =SUMIFS('Sales Master'!$C$2:$C$1054,'Sales Master'!$A$2:$A$1054,">="&A13,'Sales Master'!$A$2:$A$1054,"<="&DATE(YEAR(A13),MONTH(A13)+1,1)-1) -> 2517124.8 | D13: =SUMIFS('Sales Master'!$D$2:$D$1054,'Sales Master'!$A$2:$A$1054,">="&A13,'Sales Master'!$A$2:$A$1054,"<="&DATE(YEAR(A13),MONTH(A13)+1,1)-1) -> 68569 | E13: =B13-C13 -> 114228.51 | F13: =E13/B13 -> 0.043410554 | G13: =B13/D13 -> 38.375262
... A37: 42675 | B37: =SUMIFS('Sales Master'!$B$2:$B$1054,'Sales Master'!$A$2:$A$1054,">="&A37,'Sales Master'!$A$2:$A$1054,"<="&DATE(YEAR(A37),MONTH(A37)+1,1)-1) -> 1851029.9 | C37: =SUMIFS('Sales Master'!$C$2:$C$1054,'Sales Master'!$A$2:$A$1054,">="&A37,'Sales Master'!$A$2:$A$1054,"<="&DATE(YEAR(A37),MONTH(A37)+1,1)-1) -> 1724472.9 | D37: =SUMIFS('Sales Master'!$D$2:$D$1054,'Sales Master'!$A$2:$A$1054,">="&A37,'Sales Master'!$A$2:$A$1054,"<="&DATE(YEAR(A37),MONTH(A37)+1,1)-1) -> 43107 | E37: =B37-C37 -> 126556.98 | F37: =E37/B37 -> 0.06837112 | G37: =B37/D37 -> 42.940355

Sheet Day of Week Pivot
A1: Day of Week | B1: Avg Quantity Sold | C1: Avg Price per Unit (R) | D1: Avg Gross Profit (R) | E1: Trading Days (n)
A2: Monday | B2: =SUMPRODUCT(('Sales Master'!$A$2:$A$1054)*0+(TEXT('Sales Master'!$A$2:$A$1054,"dddd")=$A2)*'Sales Master'!$D$2:$D$1054)/SUMPRODUCT((TEXT('Sales Master'!$A$2:$A$1054,"dddd")=$A2)*1) -> 4400.0464 | C2: =SUMPRODUCT((TEXT('Sales Master'!$A$2:$A$1054,"dddd")=$A2)*'Sales Master'!$E$2:$E$1054)/SUMPRODUCT((TEXT('Sales Master'!$A$2:$A$1054,"dddd")=$A2)*1) -> 37.242813 | D2: =SUMPRODUCT((TEXT('Sales Master'!$A$2:$A$1054,"dddd")=$A2)*'Sales Master'!$G$2:$G$1054)/SUMPRODUCT((TEXT('Sales Master'!$A$2:$A$1054,"dddd")=$A2)*1) -> -5108.2543 | E2: =SUMPRODUCT((TEXT('Sales Master'!$A$2:$A$1054,"dddd")=$A2)*1) -> 151
A3: Tuesday | B3: =SUMPRODUCT(('Sales Master'!$A$2:$A$1054)*0+(TEXT('Sales Master'!$A$2:$A$1054,"dddd")=$A3)*'Sales Master'!$D$2:$D$1054)/SUMPRODUCT((TEXT('Sales Master'!$A$2:$A$1054,"dddd")=$A3)*1) -> 3851.702 | C3: =SUMPRODUCT((TEXT('Sales Master'!$A$2:$A$1054,"dddd")=$A3)*'Sales Master'!$E$2:$E$1054)/SUMPRODUCT((TEXT('Sales Master'!$A$2:$A$1054,"dddd")=$A3)*1) -> 37.232696 | D3: =SUMPRODUCT((TEXT('Sales Master'!$A$2:$A$1054,"dddd")=$A3)*'Sales Master'!$G$2:$G$1054)/SUMPRODUCT((TEXT('Sales Master'!$A$2:$A$1054,"dddd")=$A3)*1) -> -4551.1806 | E3: =SUMPRODUCT((TEXT('Sales Master'!$A$2:$A$1054,"dddd")=$A3)*1) -> 151
A4: Wednesday | B4: =SUMPRODUCT(('Sales Master'!$A$2:$A$1054)*0+(TEXT('Sales Master'!$A$2:$A$1054,"dddd")=$A4)*'Sales Master'!$D$2:$D$1054)/SUMPRODUCT((TEXT('Sales Master'!$A$2:$A$1054,"dddd")=$A4)*1) -> 4105.9934 | C4: =SUMPRODUCT((TEXT('Sales Master'!$A$2:$A$1054,"dddd")=$A4)*'Sales Master'!$E$2:$E$1054)/SUMPRODUCT((TEXT('Sales Master'!$A$2:$A$1054,"dddd")=$A4)*1) -> 37.015791 | D4: =SUMPRODUCT((TEXT('Sales Master'!$A$2:$A$1054,"dddd")=$A4)*'Sales Master'!$G$2:$G$1054)/SUMPRODUCT((TEXT('Sales Master'!$A$2:$A$1054,"dddd")=$A4)*1) -> -5930.0708 | E4: =SUMPRODUCT((TEXT('Sales Master'!$A$2:$A$1054,"dddd")=$A4)*1) -> 151
A5: Thursday | B5: =SUMPRODUCT(('Sales Master'!$A$2:$A$1054)*0+(TEXT('Sales Master'!$A$2:$A$1054,"dddd")=$A5)*'Sales Master'!$D$2:$D$1054)/SUMPRODUCT((TEXT('Sales Master'!$A$2:$A$1054,"dddd")=$A5)*1) -> 3969.22 | C5: =SUMPRODUCT((TEXT('Sales Master'!$A$2:$A$1054,"dddd")=$A5)*'Sales Master'!$E$2:$E$1054)/SUMPRODUCT((TEXT('Sales Master'!$A$2:$A$1054,"dddd")=$A5)*1) -> 37.161422 | D5: =SUMPRODUCT((TEXT('Sales Master'!$A$2:$A$1054,"dddd")=$A5)*'Sales Master'!$G$2:$G$1054)/SUMPRODUCT((TEXT('Sales Master'!$A$2:$A$1054,"dddd")=$A5)*1) -> -5161.5533 | E5: =SUMPRODUCT((TEXT('Sales Master'!$A$2:$A$1054,"dddd")=$A5)*1) -> 150
A6: Friday | B6: =SUMPRODUCT(('Sales Master'!$A$2:$A$1054)*0+(TEXT('Sales Master'!$A$2:$A$1054,"dddd")=$A6)*'Sales Master'!$D$2:$D$1054)/SUMPRODUCT((TEXT('Sales Master'!$A$2:$A$1054,"dddd")=$A6)*1) -> 6955.3933 | C6: =SUMPRODUCT((TEXT('Sales Master'!$A$2:$A$1054,"dddd")=$A6)*'Sales Master'!$E$2:$E$1054)/SUMPRODUCT((TEXT('Sales Master'!$A$2:$A$1054,"dddd")=$A6)*1) -> 36.982263 | D6: =SUMPRODUCT((TEXT('Sales Master'!$A$2:$A$1054,"dddd")=$A6)*'Sales Master'!$G$2:$G$1054)/SUMPRODUCT((TEXT('Sales Master'!$A$2:$A$1054,"dddd")=$A6)*1) -> -9490.1188 | E6: =SUMPRODUCT((TEXT('Sales Master'!$A$2:$A$1054,"dddd")=$A6)*1) -> 150
A7: Saturday | B7: =SUMPRODUCT(('Sales Master'!$A$2:$A$1054)*0+(TEXT('Sales Master'!$A$2:$A$1054,"dddd")=$A7)*'Sales Master'!$D$2:$D$1054)/SUMPRODUCT((TEXT('Sales Master'!$A$2:$A$1054,"dddd")=$A7)*1) -> 7937.3067 | C7: =SUMPRODUCT((TEXT('Sales Master'!$A$2:$A$1054,"dddd")=$A7)*'Sales Master'!$E$2:$E$1054)/SUMPRODUCT((TEXT('Sales Master'!$A$2:$A$1054,"dddd")=$A7)*1) -> 36.857654 | D7: =SUMPRODUCT((TEXT('Sales Master'!$A$2:$A$1054,"dddd")=$A7)*'Sales Master'!$G$2:$G$1054)/SUMPRODUCT((TEXT('Sales Master'!$A$2:$A$1054,"dddd")=$A7)*1) -> -11996.077 | E7: =SUMPRODUCT((TEXT('Sales Master'!$A$2:$A$1054,"dddd")=$A7)*1) -> 150
A8: Sunday | B8: =SUMPRODUCT(('Sales Master'!$A$2:$A$1054)*0+(TEXT('Sales Master'!$A$2:$A$1054,"dddd")=$A8)*'Sales Master'!$D$2:$D$1054)/SUMPRODUCT((TEXT('Sales Master'!$A$2:$A$1054,"dddd")=$A8)*1) -> 3897.1 | C8: =SUMPRODUCT((TEXT('Sales Master'!$A$2:$A$1054,"dddd")=$A8)*'Sales Master'!$E$2:$E$1054)/SUMPRODUCT((TEXT('Sales Master'!$A$2:$A$1054,"dddd")=$A8)*1) -> 37.015503 | D8: =SUMPRODUCT((TEXT('Sales Master'!$A$2:$A$1054,"dddd")=$A8)*'Sales Master'!$G$2:$G$1054)/SUMPRODUCT((TEXT('Sales Master'!$A$2:$A$1054,"dddd")=$A8)*1) -> -5100.6895 | E8: =SUMPRODUCT((TEXT('Sales Master'!$A$2:$A$1054,"dddd")=$A8)*1) -> 150
